businessman/__init__.py
businessman/errors.py
businessman/business_logic/__init__.py
businessman/business_logic/base_business_logic.py
businessman/business_logic/base_crud_business_logic.py
businessman/business_logic/utils.py
businessman/mongo/__init__.py
businessman/restix_api/__init__.py
businessman/restix_api/utils.py
businessman/restx_api/__init__.py
businessman/restx_api/custom_field.py
businessman/restx_api/factory_func.py
businessman-0.0.30.dist-info/LICENSE
businessman-0.0.30.dist-info/METADATA
businessman-0.0.30.dist-info/WHEEL
businessman-0.0.30.dist-info/top_level.txt
businessman-0.0.30.dist-info/RECORD
